LICENSE
MANIFEST.in
README.md
requirements.txt
setup.py
jsonargon/__init__.py
jsonargon/decorators.py
jsonargon/deserializer.py
jsonargon/serializer.py
jsonargon.egg-info/PKG-INFO
jsonargon.egg-info/SOURCES.txt
jsonargon.egg-info/dependency_links.txt
jsonargon.egg-info/top_level.txt
jsonargon/fields/__init__.py
jsonargon/fields/dict.py
jsonargon/fields/list.py
jsonargon/fields/simple.py
jsonargon/resources/readme.txt
jsonargon/serialization/__init__.py
jsonargon/serialization/dictionary.py