Metadata-Version: 2.1
Name: jsonargon
Version: 0.1.0
Summary: Serialization and deserialization of JSON objects from/into Python objects (with validation and remapping capabilities)
Home-page: https://gitlab.com/federico_pugliese/jsonargon
Author: Federico Pugliese
License: Apache Software License, Version 2.0
Platform: UNKNOWN
Classifier: License :: OSI Approved :: Apache Software License
Classifier: Development Status :: 3 - Alpha
Classifier: Intended Audience :: Developers
Classifier: Programming Language :: Python :: 3
Classifier: Programming Language :: Python :: 3.7
